CHANGES.txt
MANIFEST.in
README.txt
setup.py
version.txt
src/typhoonae/__init__.py
src/typhoonae/apptool.py
src/typhoonae/capability_stub.py
src/typhoonae/fcgiserver.py
src/typhoonae/remote_pdb.py
src/typhoonae/runtask.py
src/typhoonae.egg-info/PKG-INFO
src/typhoonae.egg-info/SOURCES.txt
src/typhoonae.egg-info/dependency_links.txt
src/typhoonae.egg-info/entry_points.txt
src/typhoonae.egg-info/not-zip-safe
src/typhoonae.egg-info/requires.txt
src/typhoonae.egg-info/top_level.txt
src/typhoonae/appcfg/__init__.py
src/typhoonae/appcfg/index.html
src/typhoonae/appcfg/service.py
src/typhoonae/blobstore/__init__.py
src/typhoonae/blobstore/blobstore_stub.py
src/typhoonae/blobstore/file_blob_storage.py
src/typhoonae/blobstore/handlers.py
src/typhoonae/blobstore/tests/__init__.py
src/typhoonae/blobstore/tests/test_blobstore.py
src/typhoonae/blobstore/tests/test/1/0000000001
src/typhoonae/channel/__init__.py
src/typhoonae/channel/channel_service_stub.py
src/typhoonae/channel/jsapi.py
src/typhoonae/channel/tae-channel-js.js
src/typhoonae/channel/tests/__init__.py
src/typhoonae/channel/tests/test_channel.py
src/typhoonae/handlers/__init__.py
src/typhoonae/handlers/devnull.py
src/typhoonae/handlers/dummy.png
src/typhoonae/handlers/images.py
src/typhoonae/handlers/json_rpc.py
src/typhoonae/handlers/login.py
src/typhoonae/handlers/tests/__init__.py
src/typhoonae/handlers/tests/test_handlers.py
src/typhoonae/handlers/tests/test_json_rpc.py
src/typhoonae/mail/__init__.py
src/typhoonae/mail/imap_http_dispatch.py
src/typhoonae/mail/imaplib2.py
src/typhoonae/memcache/__init__.py
src/typhoonae/memcache/memcache_stub.py
src/typhoonae/memcache/tests/__init__.py
src/typhoonae/memcache/tests/test_memcache.py
src/typhoonae/mongodb/__init__.py
src/typhoonae/mongodb/datastore_mongo_stub.py
src/typhoonae/mongodb/tests/__init__.py
src/typhoonae/mongodb/tests/index.yaml
src/typhoonae/mongodb/tests/test_datastore_mongo.py
src/typhoonae/mysql/__init__.py
src/typhoonae/mysql/datastore_mysql_stub.py
src/typhoonae/mysql/tests/__init__.py
src/typhoonae/mysql/tests/index.yaml
src/typhoonae/mysql/tests/test_datastore_mysql.py
src/typhoonae/taskqueue/__init__.py
src/typhoonae/taskqueue/celery_tasks.py
src/typhoonae/taskqueue/deferred_worker.py
