Metadata-Version: 1.0
Name: typhoonae
Version: 0.2.0
Summary: Typhoon App Engine.
Home-page: http://code.google.com/p/typhoonae
Author: Tobias Rodaebel
Author-email: tobias dot rodaebel at googlemail dot com
License: Apache License 2.0
Keywords: gae,appengine,wsgi,fastcgi
Platform: UNKNOWN
Classifier: Development Status :: 4 - Beta
Classifier: Environment :: Web Environment
Classifier: Intended Audience :: Developers
Classifier: License :: OSI Approved :: Apache Software License
Classifier: Natural Language :: English
Classifier: Operating System :: MacOS :: MacOS X
Classifier: Operating System :: POSIX :: Linux
Classifier: Programming Language :: Python
Classifier: Topic :: Internet :: WWW/HTTP :: WSGI :: Server
